caf/distribute/__init__.py
caf/distribute/_version.py
caf/distribute/array_utils.py
caf/distribute/cost_functions.py
caf/distribute/furness.py
caf/distribute/iterative_proportional_fitting.py
caf/distribute/py.typed
caf/distribute/utils.py
caf/distribute/gravity_model/__init__.py
caf/distribute/gravity_model/core.py
caf/distribute/gravity_model/multi_area.py
caf/distribute/gravity_model/single_area.py
caf_distribute-0.7.0.dist-info/licenses/LICENSE
caf_distribute-0.7.0.dist-info/METADATA
caf_distribute-0.7.0.dist-info/WHEEL
caf_distribute-0.7.0.dist-info/top_level.txt
caf_distribute-0.7.0.dist-info/RECORD
