Metadata-Version: 2.4
Name: caf.distribute
Version: 0.7.0
Summary: Methods to distribute values across arrays
Author: Transport for the North
License: Copyright © Transport for the North (“TfN”) (2023).
Project-URL: Bug Tracker, https://github.com/Transport-for-the-North/caf.distribute/issues
Project-URL: Homepage, https://github.com/Transport-for-the-North/caf.distribute
Project-URL: Source, https://github.com/Transport-for-the-North/caf.distribute
Project-URL: Documentation, http://cafdistribute.rtfd.io/
Classifier: Programming Language :: Python :: 3 :: Only
Classifier: Programming Language :: Python :: 3.11
Classifier: Programming Language :: Python :: 3.12
Classifier: Programming Language :: Python :: 3.13
Requires-Python: >=3.11
License-File: LICENSE
Requires-Dist: numpy>=2.2
Requires-Dist: scipy>=1.14
Requires-Dist: pandas>=2
Requires-Dist: tqdm>=4.50.2
Requires-Dist: caf.toolkit>=0.11
Requires-Dist: matplotlib>=3.8.2
Requires-Dist: xarray>=2024
Provides-Extra: dev
Requires-Dist: black>=23.12.1; extra == "dev"
Requires-Dist: isort>=5.12.0; extra == "dev"
Requires-Dist: mypy>=1.0.0; extra == "dev"
Requires-Dist: mypy_extensions>=1.0.0; extra == "dev"
Requires-Dist: pydocstyle[toml]>=6.1.1; extra == "dev"
Requires-Dist: pylint==3.2; extra == "dev"
Requires-Dist: pytest>=7.4.0; extra == "dev"
Requires-Dist: pytest-cov>=4.1.0; extra == "dev"
Requires-Dist: pytest-xdist>=3.3.1; extra == "dev"
Requires-Dist: versioningit>=2.2.0; extra == "dev"
Provides-Extra: docs
Requires-Dist: sphinx-automodapi>=0.16.0; extra == "docs"
Requires-Dist: pydata-sphinx-theme>=0.14.1; extra == "docs"
Requires-Dist: graphviz>=0.20.1; extra == "docs"
Requires-Dist: versioningit<4.0.0,>=2.2.0; extra == "docs"
Provides-Extra: sparse
Requires-Dist: sparse>=0.15.4; extra == "sparse"
Requires-Dist: numba>=0.60.0; extra == "sparse"
Dynamic: license-file
